ir_client/__init__.py
ir_client/cars/__init__.py
ir_client/cars/mappers.py
ir_client/cars/models.py
ir_client/endpoint_parameters.py
ir_client/endpoint_types.py
ir_client/exceptions.py
ir_client/iracing_client.py
ir_client/laps/__init__.py
ir_client/laps/mappers.py
ir_client/laps/models.py
ir_client/series_race_results/__init__.py
ir_client/series_race_results/mappers.py
ir_client/series_race_results/models.py
ir_client/session_parameters.py
ir_client/subsession_results/__init__.py
ir_client/subsession_results/mappers.py
ir_client/subsession_results/models.py
ir_client/utils/__init__.py
ir_client/utils/collections.py
ir_client/utils/datetime_utils.py
ir_client/utils/enum_utils.py
ir_client/utils/iterutils.py
ir_client/utils/url_utils.py
ir_client-0.1.6.dist-info/LICENSE
ir_client-0.1.6.dist-info/METADATA
ir_client-0.1.6.dist-info/WHEEL
ir_client-0.1.6.dist-info/RECORD
