Metadata-Version: 2.1
Name: ir-client
Version: 0.1.6
Summary: Library to access the iRacing web API
License: MIT
Author: Sascha Lamp
Author-email: sascha@lamp-online.de
Requires-Python: >=3.10,<4.0
Classifier: License :: OSI Approved :: MIT License
Classifier: Programming Language :: Python :: 3
Classifier: Programming Language :: Python :: 3.10
Classifier: Programming Language :: Python :: 3.11
Requires-Dist: assertpy (>=1.1,<2.0)
Requires-Dist: beautifulsoup4 (>=4.12.2,<5.0.0)
Requires-Dist: requests (>=2.31.0,<3.0.0)
